weather/__init__.py
weather/exceptions.py
weather/geolocation_client.py
weather/weather_client.py
einenlum_weather_project-0.0.2.dist-info/WHEEL
einenlum_weather_project-0.0.2.dist-info/METADATA
einenlum_weather_project-0.0.2.dist-info/RECORD
